.latest-version.generated.txt
LICENSE
README.md
pyproject.toml
src/chatterbox_vllm/__init__.py
src/chatterbox_vllm/text_utils.py
src/chatterbox_vllm/tts.py
src/chatterbox_vllm.egg-info/PKG-INFO
src/chatterbox_vllm.egg-info/SOURCES.txt
src/chatterbox_vllm.egg-info/dependency_links.txt
src/chatterbox_vllm.egg-info/requires.txt
src/chatterbox_vllm.egg-info/top_level.txt
src/chatterbox_vllm/models/s3gen/__init__.py
src/chatterbox_vllm/models/s3gen/const.py
src/chatterbox_vllm/models/s3gen/decoder.py
src/chatterbox_vllm/models/s3gen/f0_predictor.py
src/chatterbox_vllm/models/s3gen/flow.py
src/chatterbox_vllm/models/s3gen/flow_matching.py
src/chatterbox_vllm/models/s3gen/hifigan.py
src/chatterbox_vllm/models/s3gen/s3gen.py
src/chatterbox_vllm/models/s3gen/xvector.py
src/chatterbox_vllm/models/s3gen/matcha/decoder.py
src/chatterbox_vllm/models/s3gen/matcha/flow_matching.py
src/chatterbox_vllm/models/s3gen/matcha/text_encoder.py
src/chatterbox_vllm/models/s3gen/matcha/transformer.py
src/chatterbox_vllm/models/s3gen/transformer/__init__.py
src/chatterbox_vllm/models/s3gen/transformer/activation.py
src/chatterbox_vllm/models/s3gen/transformer/attention.py
src/chatterbox_vllm/models/s3gen/transformer/convolution.py
src/chatterbox_vllm/models/s3gen/transformer/embedding.py
src/chatterbox_vllm/models/s3gen/transformer/encoder_layer.py
src/chatterbox_vllm/models/s3gen/transformer/positionwise_feed_forward.py
src/chatterbox_vllm/models/s3gen/transformer/subsampling.py
src/chatterbox_vllm/models/s3gen/transformer/upsample_encoder.py
src/chatterbox_vllm/models/s3gen/utils/class_utils.py
src/chatterbox_vllm/models/s3gen/utils/mask.py
src/chatterbox_vllm/models/s3gen/utils/mel.py
src/chatterbox_vllm/models/s3tokenizer/__init__.py
src/chatterbox_vllm/models/s3tokenizer/s3tokenizer.py
src/chatterbox_vllm/models/t3/__init__.py
src/chatterbox_vllm/models/t3/entokenizer.py
src/chatterbox_vllm/models/t3/t3.py
src/chatterbox_vllm/models/t3/tokenizer.json
src/chatterbox_vllm/models/t3/modules/cond_enc.py
src/chatterbox_vllm/models/t3/modules/learned_pos_emb.py
src/chatterbox_vllm/models/t3/modules/perceiver.py
src/chatterbox_vllm/models/t3/modules/t3_config.py
