Metadata-Version: 2.4
Name: chatterbox-vllm
Version: 0.1.5
Summary: Chatterbox TTS ported to VLLM for efficienct and advanced inference tasks
Author-email: David Li <david@david-li.com>, resemble-ai <engineering@resemble.ai>
License: MIT License
Project-URL: Changelog, https://github.com/randombk/chatterbox-vllm/blob/master/README.md
Project-URL: Source, https://github.com/randombk/chatterbox-vllm
Project-URL: Tracker, https://github.com/randombk/chatterbox-vllm/issues
Keywords: llm,gpt,cli,tts,chatterbox
Requires-Python: >=3.10
License-File: LICENSE
Requires-Dist: torch
Requires-Dist: torchaudio
Requires-Dist: transformers<4.54.0
Requires-Dist: tokenizers
Requires-Dist: scipy
Requires-Dist: numpy
Requires-Dist: librosa
Requires-Dist: s3tokenizer
Requires-Dist: omegaconf
Requires-Dist: conformer
Requires-Dist: diffusers
Requires-Dist: vllm
Requires-Dist: peft
Requires-Dist: llvmlite>=0.44.0
Requires-Dist: vllm==0.10.0
Requires-Dist: gradio
Provides-Extra: dev
Requires-Dist: build; extra == "dev"
Requires-Dist: twine; extra == "dev"
Dynamic: license-file
